{
  "updated_at": "2026-07-04T04:58:42.431468+09:00",
  "accuracy": {
    "total": 47,
    "correct": 11,
    "rate": 23
  },
  "wti_price": 69.01000213623047,
  "articles": [
    {
      "id": "https://www.rigzone.com/news/exxonmobil_qatarenergy_affirm_commerciality_of_cyprus_discoveries-03-jul-2026-184052-article/?rss=true",
      "source": "Rigzone",
      "title": "ExxonMobil, QatarEnergy Affirm Commerciality of Cyprus Discoveries",
      "summary": "ExxonMobil とQatarEnergyがキプロス東地中海ガス田の商業化宣言",
      "link": "https://www.rigzone.com/news/exxonmobil_qatarenergy_affirm_commerciality_of_cyprus_discoveries-03-jul-2026-184052-article/?rss=true",
      "pub": "Fri, 03 Jul 2026 09:23:25 GMT",
      "pub_ts": 1783070605,
      "impact": 4,
      "impact_group": "high",
      "direction": "bullish",
      "time_horizon": "medium",
      "main_factor": "供給確保（新規発見）",
      "reliability": "A",
      "is_new": false,
      "verified": false,
      "correct": null
    },
    {
      "id": "https://oilprice.com/Energy/Energy-General/Tehran-Is-Racing-the-Clock-to-Export-as-Much-Oil-as-Possible.html",
      "source": "OilPrice.com",
      "title": "Tehran Is Racing the Clock to Export as Much Oil as Possible",
      "summary": "イランが米国との60日間交渉期間中に原油輸出を急速に増加させている。制裁解除により供給増加が確定的。",
      "link": "https://oilprice.com/Energy/Energy-General/Tehran-Is-Racing-the-Clock-to-Export-as-Much-Oil-as-Possible.html",
      "pub": "Thu, 02 Jul 2026 17:00:00 -0500",
      "pub_ts": 1783029600,
      "impact": 4,
      "impact_group": "high",
      "direction": "bearish",
      "time_horizon": "medium",
      "main_factor": "供給増加",
      "reliability": "B",
      "is_new": false,
      "verified": false,
      "correct": null
    },
    {
      "id": "https://oilprice.com/Latest-Energy-News/World-News/Iran-Tightens-Grip-on-Strait-of-Hormuz-Tanker-Traffic.html",
      "source": "OilPrice.com",
      "title": "Iran Tightens Grip on Strait of Hormuz Tanker Traffic",
      "summary": "イランがホルムズ海峡の石油タンカー航行をテヘランが承認するルート限定に警告。供給リスク上昇。",
      "link": "https://oilprice.com/Latest-Energy-News/World-News/Iran-Tightens-Grip-on-Strait-of-Hormuz-Tanker-Traffic.html",
      "pub": "Thu, 02 Jul 2026 13:30:00 -0500",
      "pub_ts": 1783017000,
      "impact": 4,
      "impact_group": "high",
      "direction": "bullish",
      "time_horizon": "short",
      "main_factor": "地政学リスク",
      "reliability": "B",
      "is_new": false,
      "verified": true,
      "correct": true
    },
    {
      "id": "https://oilprice.com/Latest-Energy-News/World-News/OPEC-Oil-Production-Jumps-But-Gulf-Supply-Is-Still-Far-From-Normal.html",
      "source": "OilPrice.com",
      "title": "OPEC Oil Production Jumps, But Gulf Supply Is Still Far From Normal",
      "summary": "OPEC6月産油量が回復したが、湾岸地域の供給は依然戦前水準に遠く及ばず。",
      "link": "https://oilprice.com/Latest-Energy-News/World-News/OPEC-Oil-Production-Jumps-But-Gulf-Supply-Is-Still-Far-From-Normal.html",
      "pub": "Fri, 03 Jul 2026 14:30:00 -0500",
      "pub_ts": 1783107000,
      "impact": 3,
      "impact_group": "mid",
      "direction": "bearish",
      "time_horizon": "short",
      "main_factor": "供給回復",
      "reliability": "B",
      "is_new": true,
      "verified": false,
      "correct": null
    },
    {
      "id": "https://oilprice.com/Metals/Commodities/Coppers-Next-Move-Depends-On-Washington-Not-The-Strait-Of-Hormuz.html",
      "source": "OilPrice.com",
      "title": "Copper's Next Move Depends On Washington, Not The Strait Of Hormuz",
      "summary": "イラン軍とイラン外務省の声明に矛盾。ホルムズ海峡の開閉状況が不透明で、市場の確実性が低い",
      "link": "https://oilprice.com/Metals/Commodities/Coppers-Next-Move-Depends-On-Washington-Not-The-Strait-Of-Hormuz.html",
      "pub": "Fri, 03 Jul 2026 14:00:00 -0500",
      "pub_ts": 1783105200,
      "impact": 3,
      "impact_group": "mid",
      "direction": "neutral",
      "time_horizon": "short",
      "main_factor": "地政学リスク",
      "reliability": "B",
      "is_new": false,
      "verified": false,
      "correct": null
    },
    {
      "id": "https://oilprice.com/Latest-Energy-News/World-News/Russia-Scrambles-for-Asian-Jet-Fuel-as-Crisis-Deepens.html",
      "source": "OilPrice.com",
      "title": "Russia Scrambles for Asian Jet Fuel as Crisis Deepens",
      "summary": "ロシアが日本発のジェット燃料を輸入予定。複雑な流通経路を通じて最低20万バレル受け取り見込み。",
      "link": "https://oilprice.com/Latest-Energy-News/World-News/Russia-Scrambles-for-Asian-Jet-Fuel-as-Crisis-Deepens.html",
      "pub": "Fri, 03 Jul 2026 12:30:00 -0500",
      "pub_ts": 1783099800,
      "impact": 3,
      "impact_group": "mid",
      "direction": "bearish",
      "time_horizon": "short",
      "main_factor": "供給不足、地政学リスク",
      "reliability": "B",
      "is_new": false,
      "verified": false,
      "correct": null
    },
    {
      "id": "https://oilprice.com/Geopolitics/International/Russia-Escalates-Kyiv-Strikes-Days-Before-NATO-Summit-Showdown.html",
      "source": "OilPrice.com",
      "title": "Russia Escalates Kyiv Strikes Days Before NATO Summit Showdown",
      "summary": "ロシアがキーウに大規模攻撃。NATOサミット前の地政学的緊張が高まり、対ロシア経済制裁強化の圧力増加。",
      "link": "https://oilprice.com/Geopolitics/International/Russia-Escalates-Kyiv-Strikes-Days-Before-NATO-Summit-Showdown.html",
      "pub": "Fri, 03 Jul 2026 11:00:00 -0500",
      "pub_ts": 1783094400,
      "impact": 3,
      "impact_group": "mid",
      "direction": "bullish",
      "time_horizon": "short",
      "main_factor": "地政学リスク",
      "reliability": "B",
      "is_new": false,
      "verified": false,
      "correct": null
    },
    {
      "id": "https://oilprice.com/Latest-Energy-News/World-News/Citi-Oil-Could-Sink-to-60-as-Hormuz-Traffic-Normalizes.html",
      "source": "OilPrice.com",
      "title": "Citi: Oil Could Sink to $60 as Hormuz Traffic Normalizes",
      "summary": "シティグループがホルムズ海峡の通常化とイラン核合意達成を予想し、ブレント原油が年末に60ドルまで下落する可能性を指摘",
      "link": "https://oilprice.com/Latest-Energy-News/World-News/Citi-Oil-Could-Sink-to-60-as-Hormuz-Traffic-Normalizes.html",
      "pub": "Fri, 03 Jul 2026 07:00:00 -0500",
      "pub_ts": 1783080000,
      "impact": 3,
      "impact_group": "mid",
      "direction": "bearish",
      "time_horizon": "medium",
      "main_factor": "供給リスク低下、イラン核合意",
      "reliability": "B",
      "is_new": false,
      "verified": false,
      "correct": null
    },
    {
      "id": "https://oilprice.com/Latest-Energy-News/World-News/Oil-Set-for-Fourth-Straight-Weekly-Loss-as-Hormuz-Flows-Return.html",
      "source": "OilPrice.com",
      "title": "Oil Set for Fourth Straight Weekly Loss as Hormuz Flows Return",
      "summary": "ホルムズ海峡の暫定的な再開と石油流入増加により、WTIは4週連続の週間下落を記録見込み",
      "link": "https://oilprice.com/Latest-Energy-News/World-News/Oil-Set-for-Fourth-Straight-Weekly-Loss-as-Hormuz-Flows-Return.html",
      "pub": "Fri, 03 Jul 2026 05:00:00 -0500",
      "pub_ts": 1783072800,
      "impact": 3,
      "impact_group": "mid",
      "direction": "bearish",
      "time_horizon": "short",
      "main_factor": "供給増加、地政学リスク緩和",
      "reliability": "B",
      "is_new": false,
      "verified": false,
      "correct": null
    },
    {
      "id": "https://oilprice.com/Latest-Energy-News/World-News/PJM-on-Maximum-Alert-to-Prevent-Outages-Amid-Extreme-Heat-Wave.html",
      "source": "OilPrice.com",
      "title": "PJM on Maximum Alert to Prevent Outages Amid Extreme Heat Wave",
      "summary": "米国で極度の熱波に対応し電力最大供給警報。石油需要増加の可能性",
      "link": "https://oilprice.com/Latest-Energy-News/World-News/PJM-on-Maximum-Alert-to-Prevent-Outages-Amid-Extreme-Heat-Wave.html",
      "pub": "Fri, 03 Jul 2026 04:00:00 -0500",
      "pub_ts": 1783069200,
      "impact": 3,
      "impact_group": "mid",
      "direction": "bullish",
      "time_horizon": "ultra_short",
      "main_factor": "需要増加（冷房需要）",
      "reliability": "B",
      "is_new": false,
      "verified": false,
      "correct": null
    },
    {
      "id": "https://www.rigzone.com/news/wire/totalenergies_offers_millions_of_iraqi_barrels_to_asia-03-jul-2026-184050-article/?rss=true",
      "source": "Rigzone",
      "title": "TotalEnergies Offers Millions of Iraqi Barrels to Asia",
      "summary": "TotalEnergiesがイラク産原油をアジア向けに大量提供。供給過剰圧力が強まる。",
      "link": "https://www.rigzone.com/news/wire/totalenergies_offers_millions_of_iraqi_barrels_to_asia-03-jul-2026-184050-article/?rss=true",
      "pub": "Fri, 03 Jul 2026 07:52:55 GMT",
      "pub_ts": 1783065175,
      "impact": 3,
      "impact_group": "mid",
      "direction": "bearish",
      "time_horizon": "short",
      "main_factor": "供給過剰",
      "reliability": "B",
      "is_new": false,
      "verified": false,
      "correct": null
    },
    {
      "id": "https://oilprice.com/Latest-Energy-News/World-News/Alberta-and-Ottawa-Greenlight-New-Pacific-Pipeline.html",
      "source": "OilPrice.com",
      "title": "Alberta and Ottawa Greenlight New Pacific Pipeline",
      "summary": "カナダがアルバータ州からカナダ太平洋沿岸への新規パイプライン建設を正式承認。アジア市場へのアクセス拡大。",
      "link": "https://oilprice.com/Latest-Energy-News/World-News/Alberta-and-Ottawa-Greenlight-New-Pacific-Pipeline.html",
      "pub": "Fri, 03 Jul 2026 02:00:00 -0500",
      "pub_ts": 1783062000,
      "impact": 3,
      "impact_group": "mid",
      "direction": "bullish",
      "time_horizon": "long",
      "main_factor": "供給ルート拡大",
      "reliability": "B",
      "is_new": false,
      "verified": false,
      "correct": null
    },
    {
      "id": "https://www.rigzone.com/news/wire/saudi_oil_exports_approach_prewar_levels-02-jul-2026-184045-article/?rss=true",
      "source": "Rigzone",
      "title": "Saudi Oil Exports Approach Pre-War Levels",
      "summary": "サウジアラビアの原油輸出がイラン戦争前の水準に回復。供給増加がWTI価格下押し圧力となる可能性。",
      "link": "https://www.rigzone.com/news/wire/saudi_oil_exports_approach_prewar_levels-02-jul-2026-184045-article/?rss=true",
      "pub": "Thu, 02 Jul 2026 20:00:00 GMT",
      "pub_ts": 1783022400,
      "impact": 3,
      "impact_group": "mid",
      "direction": "bearish",
      "time_horizon": "short",
      "main_factor": "供給回復",
      "reliability": "B",
      "is_new": false,
      "verified": false,
      "correct": null
    },
    {
      "id": "https://oilprice.com/Latest-Energy-News/World-News/Carney-Backs-BC-Tanker-Ban-as-Alberta-Unveils-Pipeline-Plan.html",
      "source": "OilPrice.com",
      "title": "Carney Backs B.C. Tanker Ban as Alberta Unveils Pipeline Plan",
      "summary": "カナダのカーニー首相がBC州タンカー禁止を支持し、アルバータ州のパイプラインプロジェクトに反対。カナダ産原油の輸出制約が強化される可能性。",
      "link": "https://oilprice.com/Latest-Energy-News/World-News/Carney-Backs-BC-Tanker-Ban-as-Alberta-Unveils-Pipeline-Plan.html",
      "pub": "Thu, 02 Jul 2026 14:30:00 -0500",
      "pub_ts": 1783020600,
      "impact": 3,
      "impact_group": "mid",
      "direction": "bearish",
      "time_horizon": "medium",
      "main_factor": "カナダ産供給制約",
      "reliability": "B",
      "is_new": false,
      "verified": true,
      "correct": false
    },
    {
      "id": "https://oilprice.com/Latest-Energy-News/World-News/Trump-Administration-Advances-New-California-Oil-Lease-Plans.html",
      "source": "OilPrice.com",
      "title": "Trump Administration Advances New California Oil Lease Plans",
      "summary": "トランプ政権がカリフォルニア州の油ガス開発リース計画を進展。36,000エーカーで30日間意見募集期間開始",
      "link": "https://oilprice.com/Latest-Energy-News/World-News/Trump-Administration-Advances-New-California-Oil-Lease-Plans.html",
      "pub": "Thu, 02 Jul 2026 12:30:00 -0500",
      "pub_ts": 1783013400,
      "impact": 3,
      "impact_group": "mid",
      "direction": "bearish",
      "time_horizon": "medium",
      "main_factor": "米国内供給増加見通し",
      "reliability": "B",
      "is_new": false,
      "verified": true,
      "correct": false
    },
    {
      "id": "https://www.reddit.com/r/oil/comments/1uln7ey/irans_floating_oil_stockpile_swells_as_major/",
      "source": "Reddit r/oil",
      "title": "Iran’s Floating Oil Stockpile Swells as Major Buyers Stay Away",
      "summary": "イラン沿岸の浮遊在庫が20百万バレル超に増加。米制裁再開前に売却困難な状況。",
      "link": "https://www.reddit.com/r/oil/comments/1uln7ey/irans_floating_oil_stockpile_swells_as_major/",
      "pub": "2026-07-02T16:33:53+00:00",
      "pub_ts": 1783010033,
      "impact": 3,
      "impact_group": "mid",
      "direction": "bearish",
      "time_horizon": "short",
      "main_factor": "供給過剰",
      "reliability": "B",
      "is_new": false,
      "verified": true,
      "correct": false
    },
    {
      "id": "https://oilprice.com/Energy/Crude-Oil/Oil-Glut-Calls-May-Be-Getting-Ahead-of-Reality.html",
      "source": "OilPrice.com",
      "title": "Oil Glut Calls May Be Getting Ahead of Reality",
      "summary": "ホルムズ海峡の流動回復報道により原油価格が下落。供給過剰懸念が浮上するも、イラン情勢リスクは残存",
      "link": "https://oilprice.com/Energy/Crude-Oil/Oil-Glut-Calls-May-Be-Getting-Ahead-of-Reality.html",
      "pub": "Thu, 02 Jul 2026 11:00:00 -0500",
      "pub_ts": 1783008000,
      "impact": 3,
      "impact_group": "mid",
      "direction": "bearish",
      "time_horizon": "short",
      "main_factor": "供給回復による過剰感",
      "reliability": "B",
      "is_new": false,
      "verified": true,
      "correct": false
    },
    {
      "id": "https://oilprice.com/Energy/Energy-General/Russias-Fuel-Crisis-Spreads-to-Central-Asia-as-Drone-Strikes-Escalate.html",
      "source": "OilPrice.com",
      "title": "Russia's Fuel Crisis Spreads to Central Asia as Drone Strikes Escalate",
      "summary": "ウクライナのドローン攻撃によるロシアの燃料危機がユーラシア地域に波及。地政学リスクは継続的だがロシア供給削減は既知",
      "link": "https://oilprice.com/Energy/Energy-General/Russias-Fuel-Crisis-Spreads-to-Central-Asia-as-Drone-Strikes-Escalate.html",
      "pub": "Thu, 02 Jul 2026 10:00:00 -0500",
      "pub_ts": 1783004400,
      "impact": 3,
      "impact_group": "mid",
      "direction": "bearish",
      "time_horizon": "medium",
      "main_factor": "地政学リスク",
      "reliability": "B",
      "is_new": false,
      "verified": true,
      "correct": false
    },
    {
      "id": "https://oilprice.com/Geopolitics/International/Russia-Ramps-Up-Pressure-on-Kyiv-With-Deadliest-Strikes-in-Months.html",
      "source": "OilPrice.com",
      "title": "Russia Ramps Up Pressure on Kyiv With Deadliest Strikes in Months",
      "summary": "ロシアがウクライナへの大規模攻撃を実施。ウクライナのドローン攻撃によるロシア製油所被害の継続が示唆される。",
      "link": "https://oilprice.com/Geopolitics/International/Russia-Ramps-Up-Pressure-on-Kyiv-With-Deadliest-Strikes-in-Months.html",
      "pub": "Thu, 02 Jul 2026 09:00:00 -0500",
      "pub_ts": 1783000800,
      "impact": 3,
      "impact_group": "mid",
      "direction": "bullish",
      "time_horizon": "short",
      "main_factor": "地政学リスク",
      "reliability": "B",
      "is_new": false,
      "verified": true,
      "correct": true
    },
    {
      "id": "https://oilprice.com/Latest-Energy-News/World-News/India-Fast-Tracks-State-Company-Stake-Sales-to-Cover-Oil-Shock-Costs.html",
      "source": "OilPrice.com",
      "title": "India Fast-Tracks State Company Stake Sales to Cover Oil Shock Costs",
      "summary": "インド政府が国営企業の株式売却で石油ショック対策資金を調達。ホルムズ海峡閉鎖の影響緩和を図る。",
      "link": "https://oilprice.com/Latest-Energy-News/World-News/India-Fast-Tracks-State-Company-Stake-Sales-to-Cover-Oil-Shock-Costs.html",
      "pub": "Thu, 02 Jul 2026 07:00:00 -0500",
      "pub_ts": 1782993600,
      "impact": 3,
      "impact_group": "mid",
      "direction": "bullish",
      "time_horizon": "medium",
      "main_factor": "地政学リスク",
      "reliability": "B",
      "is_new": false,
      "verified": true,
      "correct": true
    },
    {
      "id": "https://oilprice.com/Energy/Energy-General/Hormuz-Turns-Oil-Outlooks-Into-a-Guessing-Game.html",
      "source": "OilPrice.com",
      "title": "Hormuz Turns Oil Outlooks Into a Guessing Game",
      "summary": "エネルギー・金属市場の週間統計レポート。具体的な需給変化や価格への示唆が不明確",
      "link": "https://oilprice.com/Energy/Energy-General/Hormuz-Turns-Oil-Outlooks-Into-a-Guessing-Game.html",
      "pub": "Fri, 03 Jul 2026 13:51:36 -0500",
      "pub_ts": 1783104696,
      "impact": 2,
      "impact_group": "mid",
      "direction": "neutral",
      "time_horizon": "short",
      "main_factor": "データ集計報告",
      "reliability": "B",
      "is_new": false,
      "verified": false,
      "correct": null
    },
    {
      "id": "https://www.reddit.com/r/oil/comments/1ummjwj/is_trumps_iran_ceasefire_really_about_peace_or/",
      "source": "Reddit r/oil",
      "title": "Is Trump’s Iran ceasefire really about peace — or buying time to refill oil stocks before the next strike?",
      "summary": "トランプのイラン休戦が石油備蓄補充と次の攻撃準備の時間稼ぎではないかという個人の観測・推測",
      "link": "https://www.reddit.com/r/oil/comments/1ummjwj/is_trumps_iran_ceasefire_really_about_peace_or/",
      "pub": "2026-07-03T18:41:55+00:00",
      "pub_ts": 1783104115,
      "impact": 2,
      "impact_group": "mid",
      "direction": "bullish",
      "time_horizon": "medium",
      "main_factor": "地政学リスク",
      "reliability": "C",
      "is_new": false,
      "verified": false,
      "correct": null
    },
    {
      "id": "https://oilprice.com/Latest-Energy-News/World-News/DOJ-Urges-States-to-Enforce-Fuel-Price-Gouging-Laws.html",
      "source": "OilPrice.com",
      "title": "DOJ Urges States to Enforce Fuel Price-Gouging Laws",
      "summary": "トランプ政権がDOJに燃料価格の不当利益をめぐり州に強制措置を指示。政策的対応だが具体的な供給影響は限定的。",
      "link": "https://oilprice.com/Latest-Energy-News/World-News/DOJ-Urges-States-to-Enforce-Fuel-Price-Gouging-Laws.html",
      "pub": "Fri, 03 Jul 2026 11:30:00 -0500",
      "pub_ts": 1783096200,
      "impact": 2,
      "impact_group": "mid",
      "direction": "bearish",
      "time_horizon": "medium",
      "main_factor": "政策対応",
      "reliability": "B",
      "is_new": false,
      "verified": false,
      "correct": null
    },
    {
      "id": "https://oilprice.com/Latest-Energy-News/World-News/TotalEnergies-Offers-Millions-of-Barrels-of-Iraqi-Crude-to-Asian-Buyers.html",
      "source": "OilPrice.com",
      "title": "TotalEnergies Offers Millions of Barrels of Iraqi Crude to Asian Buyers",
      "summary": "トタルエナジーズがイラク産原油をアジア買い手に大量提供。供給動向を示す市場情報だが既知事実の範囲",
      "link": "https://oilprice.com/Latest-Energy-News/World-News/TotalEnergies-Offers-Millions-of-Barrels-of-Iraqi-Crude-to-Asian-Buyers.html",
      "pub": "Fri, 03 Jul 2026 10:30:00 -0500",
      "pub_ts": 1783092600,
      "impact": 2,
      "impact_group": "mid",
      "direction": "neutral",
      "time_horizon": "short",
      "main_factor": "供給動向",
      "reliability": "B",
      "is_new": false,
      "verified": false,
      "correct": null
    },
    {
      "id": "https://www.reddit.com/r/oil/comments/1umh82e/us_says_it_is_monitoring_oil_markets_for/",
      "source": "Reddit r/oil",
      "title": "U.S. says it is monitoring oil markets for price-fixing as it urges states to do the same",
      "summary": "米国政府が石油市場の価格操作を監視していると発表。州にも同様の監視を促す。",
      "link": "https://www.reddit.com/r/oil/comments/1umh82e/us_says_it_is_monitoring_oil_markets_for/",
      "pub": "2026-07-03T15:17:27+00:00",
      "pub_ts": 1783091847,
      "impact": 2,
      "impact_group": "mid",
      "direction": "neutral",
      "time_horizon": "medium",
      "main_factor": "規制リスク",
      "reliability": "C",
      "is_new": false,
      "verified": false,
      "correct": null
    }
  ]
}